pip_sunshine_demo/__init__.py
pip_sunshine_demo/pip_sunshine_demo.py
pip_sunshine_demo/hello_world/__init__.py
pip_sunshine_demo/hello_world/hello_world.py
pip_sunshine_demo-0.0.2.dist-info/METADATA
pip_sunshine_demo-0.0.2.dist-info/WHEEL
pip_sunshine_demo-0.0.2.dist-info/top_level.txt
pip_sunshine_demo-0.0.2.dist-info/RECORD
